datasetsync/__init__.py
datasetsync/sync.py
synctool/__init__.py
synctool/sync.py
datasetsync-0.0.1.dist-info/METADATA
datasetsync-0.0.1.dist-info/WHEEL
datasetsync-0.0.1.dist-info/top_level.txt
datasetsync-0.0.1.dist-info/RECORD
