Metadata-Version: 2.1
Name: datasetsync
Version: 0.0.1
Summary: Download dataset
Author: layerx
Author-email: <annotation.manager.dev@gmail.com>
Keywords: python,dataset,datasetsync,ai,annotation,layerx,machine learning
Classifier: Development Status :: 1 - Planning
Classifier: Intended Audience :: Developers
Classifier: Programming Language :: Python :: 3
Classifier: Operating System :: Unix
Classifier: Operating System :: MacOS :: MacOS X
Classifier: Operating System :: Microsoft :: Windows
Requires-Dist: requests
